src/__init__.py
src/driver_bts7960.py
src/example.py
bts7960_micropython-0.0.1.dist-info/METADATA
bts7960_micropython-0.0.1.dist-info/WHEEL
bts7960_micropython-0.0.1.dist-info/top_level.txt
bts7960_micropython-0.0.1.dist-info/RECORD
