Metadata-Version: 2.1
Name: bts7960-micropython
Version: 0.0.1
Summary: Project to manage H-Brigde model BTS7960 with micropython
Author: desaubv (Diego Barajas)
Author-email: desaubv@gmail.com
Project-URL: github, https://github.com/DiegoBarajas/driver_bts7960
Keywords: micropython,electronics,esp32,hbridge,h-bridge,bts7960
Classifier: Development Status :: 1 - Planning
Classifier: Intended Audience :: Developers
Classifier: Programming Language :: Python :: Implementation :: MicroPython
